skl_graph/__init__.py
skl_graph/config.py
skl_graph/version.py
skl_graph/extension/number.py
skl_graph/extension/numpy_.py
skl_graph/extension/string_.py
skl_graph/feature/edge.py
skl_graph/task/filter.py
skl_graph/task/storage.py
skl_graph/task/check/edge.py
skl_graph/task/check/graph.py
skl_graph/task/check/node.py
skl_graph/task/check/skl_map.py
skl_graph/task/plot/base.py
skl_graph/task/plot/edge.py
skl_graph/task/plot/graph.py
skl_graph/task/plot/node.py
skl_graph/type/constant.py
skl_graph/type/edge.py
skl_graph/type/feature.py
skl_graph/type/graph.py
skl_graph/type/node.py
skl_graph/type/skl_map.py
skl_graph/type/style.py
skl_graph/type/tpy_map.py
skl_graph-2024.3.dist-info/METADATA
skl_graph-2024.3.dist-info/WHEEL
skl_graph-2024.3.dist-info/top_level.txt
skl_graph-2024.3.dist-info/RECORD
