Metadata-Version: 2.1
Name: skl-graph
Version: 2024.3
Summary: SKeLeton Graph
Home-page: https://src.koda.cnrs.fr/eric.debreuve/sklgraph/
Author: Eric Debreuve
Author-email: eric.debreuve@cnrs.fr
License: CeCILL-2.1
Project-URL: Documentation, https://src.koda.cnrs.fr/eric.debreuve/sklgraph/-/wikis/home
Project-URL: Source, https://src.koda.cnrs.fr/eric.debreuve/sklgraph/
Keywords: Shape,Skeleton,Graph,Features
Classifier: Topic :: Scientific/Engineering :: Image Recognition
Classifier: Intended Audience :: Science/Research
Classifier: License :: OSI Approved :: CEA CNRS Inria Logiciel Libre License, version 2.1 (CeCILL-2.1)
Classifier: Programming Language :: Python :: 3.10
Classifier: Development Status :: 4 - Beta
Requires-Python: >=3.10
Requires-Dist: imageio
Requires-Dist: matplotlib
Requires-Dist: networkx
Requires-Dist: numpy
Requires-Dist: scikit-image
Requires-Dist: scipy
